odoo/addons/mail_activity_team/README.rst
odoo/addons/mail_activity_team/__init__.py
odoo/addons/mail_activity_team/__manifest__.py
odoo/addons/mail_activity_team/i18n/fr.po
odoo/addons/mail_activity_team/i18n/it.po
odoo/addons/mail_activity_team/i18n/mail_activity_team.pot
odoo/addons/mail_activity_team/models/__init__.py
odoo/addons/mail_activity_team/models/mail_activity.py
odoo/addons/mail_activity_team/models/mail_activity_mixin.py
odoo/addons/mail_activity_team/models/mail_activity_team.py
odoo/addons/mail_activity_team/models/mail_activity_type.py
odoo/addons/mail_activity_team/models/res_users.py
odoo/addons/mail_activity_team/readme/CONTRIBUTORS.rst
odoo/addons/mail_activity_team/readme/DESCRIPTION.rst
odoo/addons/mail_activity_team/readme/USAGE.rst
odoo/addons/mail_activity_team/security/ir.model.access.csv
odoo/addons/mail_activity_team/security/mail_activity_team_security.xml
odoo/addons/mail_activity_team/static/description/icon.png
odoo/addons/mail_activity_team/static/description/index.html
odoo/addons/mail_activity_team/static/src/js/systray.js
odoo/addons/mail_activity_team/static/src/xml/systray.xml
odoo/addons/mail_activity_team/tests/__init__.py
odoo/addons/mail_activity_team/tests/test_mail_activity_team.py
odoo/addons/mail_activity_team/views/assets_backend.xml
odoo/addons/mail_activity_team/views/mail_activity_team_views.xml
odoo/addons/mail_activity_team/views/mail_activity_type.xml
odoo/addons/mail_activity_team/views/mail_activity_views.xml
odoo/addons/mail_activity_team/views/res_users_views.xml
odoo13_addon_mail_activity_team-13.0.1.3.2.dist-info/METADATA
odoo13_addon_mail_activity_team-13.0.1.3.2.dist-info/WHEEL
odoo13_addon_mail_activity_team-13.0.1.3.2.dist-info/top_level.txt
odoo13_addon_mail_activity_team-13.0.1.3.2.dist-info/RECORD
